tensortrax/__about__.py
tensortrax/__init__.py
tensortrax/_evaluate.py
tensortrax/_helpers.py
tensortrax/_tensor.py
tensortrax/math/__init__.py
tensortrax/math/_linalg.py
tensortrax/math/_math_array.py
tensortrax/math/_math_tensor.py
tensortrax/math/_special.py
tensortrax/math/linalg/__init__.py
tensortrax/math/linalg/_linalg_array.py
tensortrax/math/linalg/_linalg_tensor.py
tensortrax/math/special/__init__.py
tensortrax/math/special/_special_tensor.py
tensortrax-0.26.2.dist-info/LICENSE
tensortrax-0.26.2.dist-info/METADATA
tensortrax-0.26.2.dist-info/WHEEL
tensortrax-0.26.2.dist-info/top_level.txt
tensortrax-0.26.2.dist-info/RECORD
