Metadata-Version: 2.2
Name: tensortrax
Version: 0.26.2
Summary: Differentiable Tensors based on NumPy Arrays
Author: Andreas Dutzler
Author-email: a.dutzler@gmail.com
License:                     GNU GENERAL PUBLIC LICENSE
Project-URL: Homepage, https://tensortrax.readthedocs.io/en/latest
Project-URL: Code, https://github.com/adtzlr/tensortrax
Project-URL: Issues, https://github.com/adtzlr/tensortrax/issues
Keywords: python,constitution,ad,automatic-differentiation,scientific-computing,tensor,calculus-of-variations,hyper-dual-numbers,hyper-dual-tensors,trailing-axes
Classifier: Development Status :: 4 - Beta
Classifier: License :: OSI Approved :: GNU General Public License v3 or later (GPLv3+)
Classifier: Operating System :: OS Independent
Classifier: Programming Language :: Python
Classifier: Programming Language :: Python :: 3
Classifier: Programming Language :: Python :: 3.9
Classifier: Programming Language :: Python :: 3.10
Classifier: Programming Language :: Python :: 3.11
Classifier: Programming Language :: Python :: 3.12
Classifier: Programming Language :: Python :: 3.13
Classifier: Topic :: Scientific/Engineering
Classifier: Topic :: Scientific/Engineering :: Mathematics
Classifier: Topic :: Utilities
Requires-Python: >=3.9
License-File: LICENSE
Requires-Dist: numpy
Requires-Dist: joblib
Provides-Extra: all
Requires-Dist: scipy; extra == "all"
Provides-Extra: docs
Requires-Dist: pydata-sphinx-theme; extra == "docs"
Requires-Dist: sphinx-autoapi; extra == "docs"
Requires-Dist: sphinx-inline-tabs; extra == "docs"
Requires-Dist: sphinx-copybutton; extra == "docs"
Requires-Dist: matplotlib; extra == "docs"
Requires-Dist: sphinx-gallery; extra == "docs"
Requires-Dist: pypandoc; extra == "docs"
